tarts/__init__.py
tarts/client.py
tarts/events.py
tarts/io_handler.py
tarts/py.typed
tarts/structs.py
tarts-0.20.1.dist-info/LICENSE
tarts-0.20.1.dist-info/METADATA
tarts-0.20.1.dist-info/WHEEL
tarts-0.20.1.dist-info/RECORD
